[
  {
    "id": "main",
    "components": [
      "section",
      "kpi-highlights-widget",
      "insurance-product-carousel-widget",
      "hero-widget",
      "blog-carousel-widget",
      "faq-widget-section"
    ]
  },
  {
    "id": "footer-template",
    "components": [
      "unipol-footer"
    ]
  },
  {
    "id": "header-template",
    "components": [
      "unipol-header"
    ]
  },
  {
    "id": "disable-add",
    "components": []
  },
  {
    "id": "section",
    "components": [
      "text",
      "image",
      "button",
      "title",
      "cards",
      "columns",
      "fragment",
      "accordion"
    ]
  },
  {
    "id": "kpi-highlights-widget",
    "components": []
  },
  {
    "id": "faq-widget-section",
    "components": []
  },
  {
    "id": "insurance-product-carousel-widget",
    "components": []
  },
  {
    "id": "faq-widget",
    "components": []
  },
  {
    "id": "blog-carousel-widget",
    "components": [
      "blog-carousel"
    ]
  },
  {
    "id": "cards",
    "components": [
      "card"
    ]
  },
  {
    "id": "columns",
    "components": [
      "column"
    ]
  },
  {
    "id": "column",
    "components": [
      "text",
      "image",
      "button",
      "title"
    ]
  },
  {
    "id": "footer-privacy-section",
    "components": [
      "footer-privacy-link"
    ]
  },
  {
    "id": "footer-social-section",
    "components": [
      "footer-social-link"
    ]
  },
  {
    "id": "full-screen-hero-carousel",
    "components": [
      "hero"
    ],
    "min": 1,
    "max": 8
  },
  {
    "id": "header-navigation-section",
    "components": [
      "header-navigation-pill-and-box"
    ]
  },
  {
    "id": "header-utilities-section",
    "components": [
      "header-utilities-navigation-pill"
    ]
  },
  {
    "id": "hero-widget",
    "components": [
      "full-screen-hero-carousel"
    ]
  },
  {
    "id": "insurance-product-carousel-widget",
    "components": []
  },
  {
    "id": "insurance-product-carousel",
    "components": [
      "insurance-product-card"
    ],
    "min": 1,
    "max": 8
  },
  {
    "id": "prodotto-unico-header",
    "components": [
      "prodotto-unico-header"
    ]
  },
  {
    "id": "options-list",
    "components": [
      "unipol-option"
    ]
  },
  {
    "id": "text-list",
    "components": [
      "text-link"
    ]
  },
  {
    "id": "options",
    "components": [
      "unipol-option"
    ]
  },
  {
    "id": "unipol-header",
    "components": [
      "header-logo",
      "header-navigation-section",
      "header-utilities-section"
    ]
  },
  {
    "id": "unipol-footer",
    "components": [
      "text-list",
      "footer-download-section",
      "footer-privacy-section",
      "footer-social-section",
      "footer-copyright-section"
    ]
  }
]