{
  "definitions": [
    {
      "title": "Icon Button",
      "id": "icon-button",
      "plugins": {
        "xwalk": {
          "page": {
            "resourceType": "core/franklin/components/icon-button/v1/icon-button",
            "template": {
              "model": "icon-button"
            }
          }
        }
      }
    }
  ],
  "models": [
    {
      "id": "icon-button",
      "fields": [
        {
          "component": "text",
          "name": "text",
          "label": "Button Text",
          "description": "Optional text to display alongside icon"
        },
        {
          "component": "text",
          "name": "icon",
          "label": "Icon",
          "required": true,
          "description": "Icon name, SVG string, or image URL"
        },
        {
          "component": "select",
          "name": "iconPosition",
          "label": "Icon Position",
          "options": [
            {
              "name": "Leading",
              "value": "leading"
            },
            {
              "name": "Trailing",
              "value": "trailing"
            },
            {
              "name": "Only",
              "value": "only"
            }
          ]
        },
        {
          "component": "select",
          "name": "variant",
          "label": "Variant",
          "options": [
            {
              "name": "Primary",
              "value": "primary"
            },
            {
              "name": "Accent",
              "value": "accent"
            },
            {
              "name": "Secondary",
              "value": "secondary"
            }
          ]
        }
      ]
    }
  ],
  "filters": [
    {
      "id": "icon-button",
      "title": "Icon Button",
      "condition": {
        "===": [
          {
            "var": "component"
          },
          "icon-button"
        ]
      }
    }
  ]
}